LICENSE
domestica/__init__.py
domestica/cli.py
domestica/client.py
domestica/constants.py
domestica/helpers.py
domestica/models.py
domestica/utils/__init__.py
domestica/utils/appdirs.py
domestica/utils/auth.py
domestica/utils/collectors.py
domestica/utils/tools.py
domestica/version.py
domestica-0.1.0.dist-info/LICENSE
domestica-0.1.0.dist-info/METADATA
domestica-0.1.0.dist-info/WHEEL
domestica-0.1.0.dist-info/entry_points.txt
domestica-0.1.0.dist-info/RECORD
